cex_adaptors/__init__.py
cex_adaptors/binance.py
cex_adaptors/bitget.py
cex_adaptors/bitmex.py
cex_adaptors/bybit.py
cex_adaptors/gateio.py
cex_adaptors/htx.py
cex_adaptors/kucoin.py
cex_adaptors/okx.py
cex_adaptors/utils.py
cex_adaptors/woo.py
cex_adaptors/exchanges/__init__.py
cex_adaptors/exchanges/auth.py
cex_adaptors/exchanges/base.py
cex_adaptors/exchanges/binance.py
cex_adaptors/exchanges/bitget.py
cex_adaptors/exchanges/bitmex.py
cex_adaptors/exchanges/bybit.py
cex_adaptors/exchanges/gateio.py
cex_adaptors/exchanges/htx.py
cex_adaptors/exchanges/kucoin.py
cex_adaptors/exchanges/okx.py
cex_adaptors/exchanges/woo.py
cex_adaptors/parsers/__init__.py
cex_adaptors/parsers/base.py
cex_adaptors/parsers/binance.py
cex_adaptors/parsers/bitget.py
cex_adaptors/parsers/bitmex.py
cex_adaptors/parsers/bybit.py
cex_adaptors/parsers/gateio.py
cex_adaptors/parsers/htx.py
cex_adaptors/parsers/kucoin.py
cex_adaptors/parsers/okx.py
cex_adaptors/parsers/woo.py
cex_services/__init__.py
cex_services/binance.py
cex_services/bitget.py
cex_services/bitmex.py
cex_services/bybit.py
cex_services/gateio.py
cex_services/htx.py
cex_services/kucoin.py
cex_services/okx.py
cex_services/utils.py
cex_services/exchanges/__init__.py
cex_services/exchanges/base.py
cex_services/exchanges/biget.py
cex_services/exchanges/binance.py
cex_services/exchanges/bitget.py
cex_services/exchanges/bitmex.py
cex_services/exchanges/bybit.py
cex_services/exchanges/gateio.py
cex_services/exchanges/htx.py
cex_services/exchanges/kucoin.py
cex_services/exchanges/okx.py
cex_services/parsers/__init__.py
cex_services/parsers/base.py
cex_services/parsers/biget.py
cex_services/parsers/binance.py
cex_services/parsers/bitget.py
cex_services/parsers/bitmex.py
cex_services/parsers/bybit.py
cex_services/parsers/gateio.py
cex_services/parsers/htx.py
cex_services/parsers/kucoin.py
cex_services/parsers/okx.py
cex_adaptors-1.0.8.dist-info/METADATA
cex_adaptors-1.0.8.dist-info/WHEEL
cex_adaptors-1.0.8.dist-info/top_level.txt
cex_adaptors-1.0.8.dist-info/RECORD
