Metadata-Version: 2.2
Name: cex-adaptors
Version: 1.0.8
Requires-Dist: aiohappyeyeballs==2.4.4
Requires-Dist: aiohttp==3.11.11
Requires-Dist: aiosignal==1.3.1
Requires-Dist: async-timeout==4.0.3
Requires-Dist: attrs==23.2.0
Requires-Dist: cfgv==3.4.0
Requires-Dist: distlib==0.3.8
Requires-Dist: filelock==3.13.1
Requires-Dist: frozenlist==1.4.1
Requires-Dist: identify==2.5.35
Requires-Dist: idna==3.6
Requires-Dist: multidict==6.0.5
Requires-Dist: nodeenv==1.8.0
Requires-Dist: numpy==2.2.2
Requires-Dist: pandas==2.2.3
Requires-Dist: platformdirs==4.2.0
Requires-Dist: pre-commit==3.6.2
Requires-Dist: propcache==0.2.1
Requires-Dist: python-dateutil==2.8.2
Requires-Dist: python-dotenv==1.0.1
Requires-Dist: pytz==2024.1
Requires-Dist: PyYAML==6.0.1
Requires-Dist: setuptools==75.8.0
Requires-Dist: six==1.16.0
Requires-Dist: tzdata==2024.1
Requires-Dist: virtualenv==20.25.1
Requires-Dist: yarl==1.18.3
Dynamic: description
Dynamic: description-content-type
Dynamic: requires-dist
